{"is_answered": true, "view_count": 153, "last_activity_date": 1477737249, "answer_count": 1, "last_edit_date": 1477737174, "link": "http://stackoverflow.com/questions/35136918/in-objective-c-fabsf-has-the-wrong-result-type", "question_id": 35136918, "tags": ["objective-c"], "creation_date": 1454348557, "accepted_answer_id": 40268713, "score": 5, "title": "In Objective-C, fabsf() has the wrong result type", "owner": {"user_id": 691977, "reputation": 838, "user_type": "registered", "accept_rate": 91, "display_name": "jalone", "link": "http://stackoverflow.com/users/691977/jalone", "profile_image": "https://www.gravatar.com/avatar/d7547928cf48f2d88c4e2c993dd3bc14?s=128&d=identicon&r=PG"}}