{"tags": ["osx", "sdk", "xcode-command-line-tools"], "is_answered": false, "creation_date": 1475159021, "view_count": 15, "score": 0, "last_activity_date": 1477679480, "title": "How to get the path to the current MacOSX SDK when only Command Line Tools are installed?", "answer_count": 1, "owner": {"user_id": 1027706, "reputation": 2590, "user_type": "registered", "accept_rate": 31, "display_name": "Ad N", "link": "http://stackoverflow.com/users/1027706/ad-n", "profile_image": "https://www.gravatar.com/avatar/ff91cf16cbd51dad8e48e2799f97e811?s=128&d=identicon&r=PG"}, "link": "http://stackoverflow.com/questions/39772978/how-to-get-the-path-to-the-current-macosx-sdk-when-only-command-line-tools-are-i", "question_id": 39772978}