{"is_answered": true, "view_count": 21, "last_activity_date": 1477693216, "answer_count": 1, "link": "http://stackoverflow.com/questions/39986422/matlab-implay-with-imcontrast", "question_id": 39986422, "tags": ["image", "matlab", "contrast"], "creation_date": 1476218734, "accepted_answer_id": 40313963, "score": 0, "title": "MATLAB: implay with imcontrast", "owner": {"user_id": 4298049, "reputation": 145, "user_type": "registered", "accept_rate": 100, "display_name": "toygan k\u0131l\u0131&#231;", "link": "http://stackoverflow.com/users/4298049/toygan-k%c4%b1l%c4%b1%c3%a7", "profile_image": "https://lh6.googleusercontent.com/-o4D_los39vM/AAAAAAAAAAI/AAAAAAAAADs/EU94ntTMzis/photo.jpg?sz=128"}}