{"is_answered": true, "view_count": 54, "last_activity_date": 1477695734, "answer_count": 2, "link": "http://stackoverflow.com/questions/37262441/sending-sms-from-uitableviewcontroller-in-swift", "question_id": 37262441, "tags": ["ios", "swift", "uitableview", "sms"], "creation_date": 1463429414, "accepted_answer_id": 37262528, "score": 0, "title": "Sending SMS from UITableViewController in Swift", "owner": {"user_id": 603367, "reputation": 31, "user_type": "registered", "accept_rate": 71, "display_name": "Szabolcs Toth", "link": "http://stackoverflow.com/users/603367/szabolcs-toth", "profile_image": "https://www.gravatar.com/avatar/9fa98adc6c84deed9510fcbd57c4dd08?s=128&d=identicon&r=PG"}}