{"answer_count": 2, "view_count": 31, "last_activity_date": 1477683644, "is_answered": true, "last_edit_date": 1477683644, "link": "http://stackoverflow.com/questions/40307099/d3-dc-js-how-to-create-a-stacked-bar-chart-while-telling-crossfilter-to-treat", "tags": ["javascript", "d3.js", "charts", "dc.js", "crossfilter"], "creation_date": 1477664266, "score": 2, "title": "d3/dc.js - How to create a stacked bar chart while telling crossfilter to treat elements in an array as separate records?", "question_id": 40307099, "owner": {"user_id": 5402754, "reputation": 33, "user_type": "registered", "display_name": "Casey", "link": "http://stackoverflow.com/users/5402754/casey", "profile_image": "https://www.gravatar.com/avatar/f1a4695139ca50788bbef564cc2e0acc?s=128&d=identicon&r=PG"}}