{"title": "Can&#39;t drag IBAction from UITapGestureRecognizer in Storyboard", "tags": ["ios", "xcode", "swift", "ibaction", "xcode-storyboard"], "creation_date": 1455316020, "score": 1, "body": "<p>As beyowulf points out in the comments above, there was a change in iOS 9 that changed how UIGestureRecognizers work with repeating content.</p>\n\n<p>This is unfortunate because I find it best practice to use storyboards over programmatic implementation, but if you're trying to figure this out here's the code:</p>\n\n<p>In your custom cell class:</p>\n\n<pre><code>override func awakeFromNib() {\n    super.awakeFromNib()\n\n    let imageViewDoubleTap = UITapGestureRecognizer(\n         target: self,\n         action:#selector(ThisClass.userSwiped)\n         )\n    imageViewDoubleTap.numberOfTapsRequired = 2\n    self.photoImageView.addGestureRecognizer(imageViewDoubleTap)\n}\n</code></pre>\n\n<p>Then create a func with the same name you provided the action parameter and implement your code in there.</p>\n", "last_activity_date": 1477078896, "answer_id": 35373283, "is_accepted": false, "owner": {"user_id": 3814160, "reputation": 899, "user_type": "registered", "accept_rate": 44, "display_name": "vikzilla", "link": "http://stackoverflow.com/users/3814160/vikzilla", "profile_image": "https://i.stack.imgur.com/vDrtU.jpg?s=128&g=1"}, "last_edit_date": 1477078896, "question_id": 35372428}