{"body": "<blockquote>\n  <p>I sometimes need to run sudo git clone since sometimes the directory where I need to make a clone requires it. Any help would be appreciated</p>\n</blockquote>\n\n<p>The folder in which you try to clone the repository into was created by root so you dont have permission to write or to create folder under it unless you are root (<code>sudo</code>), set the permissions (<code>chmod</code> or <code>chown</code>) and you will be able to clone into the folder.</p>\n\n<pre><code>chmod 755 /path\n</code></pre>\n", "tags": ["linux", "git", "ubuntu", "gnome-keyring-daemon"], "creation_date": 1460509730, "score": 0, "last_activity_date": 1460509730, "answer_id": 36586783, "is_accepted": true, "owner": {"user_id": 1755598, "reputation": 20154, "user_type": "registered", "display_name": "CodeWizard", "link": "http://stackoverflow.com/users/1755598/codewizard", "profile_image": "https://i.stack.imgur.com/S6a50.jpg?s=128&g=1"}, "title": "Error when using Git credential helper with gnome-keyring as Sudo", "question_id": 36585496}