{"title": "Is it possible to inject interface with angular2?", "tags": ["interface", "angular2", "inject"], "creation_date": 1462274048, "score": 6, "body": "<p>No, interfaces are not supported for DI. With TypeScript interfaces are not available at runtime anymore, only statically and therefore can't be used as DI tokens.</p>\n\n<p>Alternatively you can use strings as keys or <code>OpaqueToken</code></p>\n\n<pre><code>provide('CoursesServiceInterface', {useClass: CoursesServiceMock})\n</code></pre>\n\n<p>and inject it like</p>\n\n<pre><code>constructor(@Inject('CoursesServiceInterface') private coursesService:CoursesServiceInterface) {}\n</code></pre>\n\n<p>See also <a href=\"https://angular.io/docs/ts/latest/api/core/index/OpaqueToken-class.html\" rel=\"nofollow\">https://angular.io/docs/ts/latest/api/core/index/OpaqueToken-class.html</a></p>\n", "last_activity_date": 1477409227, "answer_id": 37002587, "is_accepted": false, "owner": {"user_id": 217408, "reputation": 130599, "user_type": "registered", "accept_rate": 99, "display_name": "G&#252;nter Z&#246;chbauer", "link": "http://stackoverflow.com/users/217408/g%c3%bcnter-z%c3%b6chbauer", "profile_image": "https://i.stack.imgur.com/IlnZm.jpg?s=128&g=1"}, "last_edit_date": 1477409227, "question_id": 37002522}