{"body": "<p>You need to provide the contentType in your ajax request:</p>\n\n<pre><code>contentType: 'application/json;charset=UTF-8',\n</code></pre>\n\n<p>Then in your server try to debug something like this:</p>\n\n<pre><code>request.json\n</code></pre>\n", "tags": ["python", "ajax"], "creation_date": 1472203171, "score": 0, "last_activity_date": 1472203171, "answer_id": 39162757, "is_accepted": false, "owner": {"user_id": 3767778, "reputation": 1397, "user_type": "registered", "accept_rate": 79, "display_name": "lapinkoira", "link": "http://stackoverflow.com/users/3767778/lapinkoira", "profile_image": "https://www.gravatar.com/avatar/398fc02c94b6d96a18059568f2373476?s=128&d=identicon&r=PG&f=1"}, "title": "AJAX/PYTHON : how to send json value to server", "question_id": 39162601}