{"title": "Generate static files from Angular 2 seed project", "tags": ["angular2", "angular2-seed"], "creation_date": 1474962935, "score": 0, "body": "<p>Don't put direct links to your CSS like that. Instead use project.config file to inject your CSS in your index.html. Look for this file under \"tools/config\" folder.</p>\n\n<p>See: <a href=\"https://github.com/mgechev/angular2-seed/wiki/Add-external-scripts-and-styles\" rel=\"nofollow\">https://github.com/mgechev/angular2-seed/wiki/Add-external-scripts-and-styles</a></p>\n", "last_activity_date": 1474964602, "answer_id": 39719147, "is_accepted": false, "owner": {"user_id": 29693, "reputation": 2849, "user_type": "registered", "accept_rate": 100, "display_name": "Pradeep", "link": "http://stackoverflow.com/users/29693/pradeep", "profile_image": "https://www.gravatar.com/avatar/f4e31fa5abcac146123a7a2f9fdb8f40?s=128&d=identicon&r=PG"}, "last_edit_date": 1474964602, "question_id": 39718533}