{"body": "<p>I found a solution - adding <code>isArray: true</code>. But why?</p>\n\n<pre><code>'query': { method: 'GET', isArray: true },\n</code></pre>\n", "tags": ["angularjs", "rest", "ngresource"], "creation_date": 1475780030, "score": 0, "last_activity_date": 1475780030, "answer_id": 39903640, "is_accepted": false, "owner": {"user_id": 825920, "reputation": 5410, "user_type": "registered", "accept_rate": 61, "display_name": "dc7a9163d9", "link": "http://stackoverflow.com/users/825920/dc7a9163d9", "profile_image": "https://www.gravatar.com/avatar/7a8ad6df2714b0bddeacf7a073a7a9f8?s=128&d=identicon&r=PG&f=1"}, "title": "$resource:badcfg Error in resource configuration for action `query`. Expected response to contain an object but got an array", "question_id": 39903487}