{"body": "<p>You haven't really missed anything. The <a href=\"https://github.com/topepo/caret/issues/452\" rel=\"nofollow\">question has come up before</a> and it is related to some packages create random startup messages. It took me a while to originally track it down. </p>\n", "tags": ["r", "r-caret"], "creation_date": 1476728836, "score": 1, "last_activity_date": 1476728836, "answer_id": 40093233, "is_accepted": false, "owner": {"user_id": 1078601, "reputation": 5299, "user_type": "registered", "accept_rate": 38, "display_name": "topepo", "link": "http://stackoverflow.com/users/1078601/topepo", "profile_image": "https://www.gravatar.com/avatar/c4c44c18cf9384d3caceaef88526a694?s=128&d=identicon&r=PG"}, "title": "Loading caret namespace invokes random function?", "question_id": 40026465}