{"title": "For loop (HELP on python)", "tags": ["python"], "creation_date": 1477122133, "score": -2, "body": "<pre><code>n = int(raw_input())\nfor i in xrange(0,n):\n    print \"*\",\n</code></pre>\n\n<p>This is how it works!!!</p>\n\n<p><code>raw_input()</code> is for taking input. In python, the input is taken as a string by default. So, we need to convert it to <code>int</code></p>\n\n<p><code>xrange(0,n)</code> means an iteration from 0 to n-1. </p>\n\n<p>the comma in the print statement is for printing the output on the same line. More appropriately, the <code>,</code> keeps the cursor on the present line after printing, unlike the print statement without a <code>,</code> at the end.</p>\n\n<p>Hope this helps!!!</p>\n", "last_activity_date": 1477127480, "answer_id": 40189597, "is_accepted": false, "owner": {"user_id": 6354622, "reputation": 1183, "user_type": "registered", "accept_rate": 76, "display_name": "User_Targaryen", "link": "http://stackoverflow.com/users/6354622/user-targaryen", "profile_image": "https://i.stack.imgur.com/rNoam.jpg?s=128&g=1"}, "last_edit_date": 1477127480, "question_id": 40189574}