{"body": "<p><code>s &gt; 300,000</code> is a <strong>comma expression</strong>, equivalent to <code>(s &gt; 300),000</code>. The value of a comma expression is the value of the last one in the list, here <code>000</code>. Which evaluates as <code>false</code> when converted to <code>bool</code>.</p>\n\n<p>You can write that as</p>\n\n<pre><code>if( s &gt; 300'000 )\n</code></pre>\n\n<p>or, if the compiler doesn't support that newfangled notation, as just</p>\n\n<pre><code>if( s &gt; 300000 )\n</code></pre>\n\n<p>Or you can define</p>\n\n<pre><code>double const k = 1000;\n</code></pre>\n\n<p>and write</p>\n\n<pre><code>if( s &gt; 300*k )\n</code></pre>\n\n<p>And similarly for the 25 000, 100 000 and 5000 literals.</p>\n", "tags": ["c++", "if-statement"], "creation_date": 1477253672, "score": 21, "last_activity_date": 1477253672, "answer_id": 40207364, "is_accepted": true, "owner": {"user_id": 464581, "reputation": 103573, "user_type": "registered", "accept_rate": 69, "display_name": "Cheers and hth. - Alf", "link": "http://stackoverflow.com/users/464581/cheers-and-hth-alf", "profile_image": "https://i.stack.imgur.com/v2PxU.jpg?s=128&g=1"}, "title": "If/else if always goes to else statement", "question_id": 40207327}