{"body": "<pre><code>@valid_value_regex ||= Regexp.new(self.value_regex)\nrescue =&gt; exception\nerrors.add(:value_regex, exception)\n</code></pre>\n", "tags": ["ruby-on-rails", "ruby", "regex", "ruby-on-rails-5"], "creation_date": 1477293129, "score": 0, "last_activity_date": 1477293129, "answer_id": 40212581, "is_accepted": true, "owner": {"user_id": 4201809, "reputation": 120, "user_type": "registered", "accept_rate": 92, "display_name": "Dimitri de Ruiter", "link": "http://stackoverflow.com/users/4201809/dimitri-de-ruiter", "profile_image": "https://i.stack.imgur.com/jQPMj.png?s=128&g=1"}, "title": "Rails - check if field format is valid regex / catch RegexpErrors", "question_id": 40164741}