{"body": "<p>First of all the community won't be able to help you if you don't post your code or at least your attempts. Also you need to explain your problem.</p>\n\n<p>Anyways as far as i understand your question then just put them into the same project, the program should be able to work and don't forget to import that class into the main class. </p>\n", "tags": ["java", "jcreator"], "creation_date": 1477281977, "score": 0, "last_activity_date": 1477281977, "answer_id": 40210538, "is_accepted": false, "owner": {"user_id": 7034465, "reputation": 66, "user_type": "registered", "display_name": "Saad ", "link": "http://stackoverflow.com/users/7034465/saad", "profile_image": "https://graph.facebook.com/1868403550050410/picture?type=large"}, "title": "How can I separate classes into different files?", "question_id": 40210439}