{"title": "jQuery Ajax Post - Unable to set global variable using callback function?", "tags": ["javascript", "jquery", "ajax", "asynchronous"], "creation_date": 1477334732, "score": 1, "body": "<p><code>console.log()</code> is triggered before <code>ajaxCallback()</code> and before <code>appointment</code> is set (<code>ajax</code> is asynchronous), to show <code>appointment</code> in console you can run:</p>\n\n<pre><code>function ajaxCallBack(data) {\n        var response = $.parseJSON(data.d);\n        appointment = { startDate: response.startDate, endDate: response.endDate };\n        console.log(appointment);\n}\n</code></pre>\n\n<p>or</p>\n\n<pre><code>function ajaxCallBack(data) {\n        var response = $.parseJSON(data.d);\n        appointment = { startDate: response.startDate, endDate: response.endDate };\n        printAppointment();\n}\n\n// define as global:\nfunction printAppointment() {\n    console.log(appointment)\n}\n</code></pre>\n", "last_activity_date": 1477335374, "answer_id": 40225365, "is_accepted": false, "owner": {"user_id": 6041704, "reputation": 411, "user_type": "registered", "display_name": "jonzee", "link": "http://stackoverflow.com/users/6041704/jonzee", "profile_image": "https://www.gravatar.com/avatar/07bae9f4ff0a35e195af9da7870bc006?s=128&d=identicon&r=PG&f=1"}, "last_edit_date": 1477335374, "question_id": 40225346}