{"body": "<p>The solution is to disable logging of certain requests (for example in \n<code>/etc/apache2/sites-available/000-default.conf</code> with Debian 8):</p>\n\n<pre><code>&lt;VirtualHost *:80&gt;\n  ServerName www.mywebsite.com\n  DocumentRoot /home/www/mywebsite\n  ...\n  SetEnvIf Request_URI \"^/piwik(.*)$\" dontlog\n  CustomLog ${APACHE_LOG_DIR}/other_vhosts_access.log vhost_combined env=!dontlog\n&lt;/VirtualHost&gt;\n</code></pre>\n", "tags": ["apache", "piwik"], "creation_date": 1477410459, "score": 2, "last_activity_date": 1477410459, "answer_id": 40244341, "is_accepted": true, "owner": {"user_id": 1422096, "reputation": 3378, "user_type": "registered", "accept_rate": 65, "display_name": "Basj", "link": "http://stackoverflow.com/users/1422096/basj", "profile_image": "https://www.gravatar.com/avatar/da3871bf5450fa726f20557fa3f18f51?s=128&d=identicon&r=PG"}, "title": "Don&#39;t log certain requests in Apache access.log", "question_id": 40205569}