{"body": "<p>I don't know how <em>pythonic</em> this is, but it works fine</p>\n\n<pre><code>for i in len(v)//2:\n      v[i], v[-i] = v[-i], v[i]\n</code></pre>\n", "tags": ["python", "algorithm", "indexing", "reverse"], "creation_date": 1477451990, "score": 0, "last_activity_date": 1477451990, "answer_id": 40253139, "is_accepted": false, "owner": {"user_id": 5021321, "reputation": 2041, "user_type": "registered", "accept_rate": 75, "display_name": "Eli Sadoff", "link": "http://stackoverflow.com/users/5021321/eli-sadoff", "profile_image": "https://www.gravatar.com/avatar/29f10a1b457e63d44e3a221e89e32c17?s=128&d=identicon&r=PG"}, "title": "reversing rows for indexes, python", "question_id": 40253099}