{"title": "What is the difference between &#39;\\n&#39; or &quot;\\n&quot; in C++?", "tags": ["c++", "newline"], "creation_date": 1288118855, "score": 2, "body": "<p><code>'\\n'</code> is a <code>char</code> constant.</p>\n\n<p><code>\"\\n\"</code> is a <code>const char[2]</code>.</p>\n\n<p>So usage is something like this:</p>\n\n<pre><code>char newLine = '\\n';\nconst char* charPointerStringNewLine = \"\\n\"; // implicit conversion\nconst char charStringNewLine[2] = \"\\n\";\n\nstring stringNewLine( \"\\n\" );\n</code></pre>\n\n<p>So in short: one is a pointer to a character array, the other is a single character.</p>\n", "last_activity_date": 1474617123, "answer_id": 4026940, "is_accepted": false, "owner": {"user_id": 256138, "reputation": 42076, "user_type": "registered", "accept_rate": 85, "display_name": "rubenvb", "link": "http://stackoverflow.com/users/256138/rubenvb", "profile_image": "https://www.gravatar.com/avatar/ed9e8c0ff767e38f8fade11f5af00a45?s=128&d=identicon&r=PG"}, "last_edit_date": 1474617123, "question_id": 4026887}