{"body": "<p>You could try to leverage the <a href=\"https://en.wikipedia.org/wiki/Levenshtein_distance\" rel=\"nofollow\">levenshtein</a> functionality in PHP's standard library. See here for some examples in the documentation: <a href=\"http://php.net/manual/en/function.levenshtein.php\" rel=\"nofollow\">http://php.net/manual/en/function.levenshtein.php</a></p>\n\n<p>However, this might become a very expensive calculation when your list of possible keywords grows.</p>\n\n<p>EDIT: a minimum viable example:</p>\n\n<pre><code>&lt;?php\n\n$myInput = 'persident';\n$possibleKeywords = ['tyrant', 'president', 'king', 'royal'];\n$scores = [];\n\nforeach ($possibleKeywords as $keyword) {\n    $scores[] = levenshtein($myInput, $keyword);\n}\n\necho $possibleKeywords[array_search(min($scores), $scores)];\n// prints: \"president\"\n</code></pre>\n", "tags": ["php"], "creation_date": 1477590017, "score": 1, "last_activity_date": 1477590017, "answer_id": 40291008, "is_accepted": true, "owner": {"user_id": 1182489, "reputation": 793, "user_type": "registered", "display_name": "1sloc", "link": "http://stackoverflow.com/users/1182489/1sloc", "profile_image": "https://i.stack.imgur.com/kHXvL.jpg?s=128&g=1"}, "title": "Using similar_text and strpos together", "question_id": 40290873}