{"body": "<p>This is because you create a new array. <code>[ngValue]</code> compares object identity not data content. If it gets a different object instance, it doesn't consider it the same and doesn't show it as selected.</p>\n\n<p>Either update <code>value</code> in <code>test()</code> to reflect the new selection or don't create a new array but instead just modify the previously created one.</p>\n\n<p>Actually moving </p>\n\n<pre><code>this.value = this.items[0].value;\n</code></pre>\n\n<p>to the end of the <code>test()</code> function would fix your problem.</p>\n\n<p><a href=\"http://plnkr.co/edit/JwUAEPHtniHYyMk70s7P?p=preview\" rel=\"nofollow\"><strong>Plunker example</strong></a></p>\n", "tags": ["angular2"], "creation_date": 1477634137, "score": 0, "last_activity_date": 1477634137, "answer_id": 40298882, "is_accepted": false, "owner": {"user_id": 217408, "reputation": 130599, "user_type": "registered", "accept_rate": 99, "display_name": "G&#252;nter Z&#246;chbauer", "link": "http://stackoverflow.com/users/217408/g%c3%bcnter-z%c3%b6chbauer", "profile_image": "https://i.stack.imgur.com/IlnZm.jpg?s=128&g=1"}, "title": "Lost selection after binding new items to select", "question_id": 40298736}