{"body": "<p>Actually, issue was not created by errbit. I am using <strong>mailboxer</strong> gem , which has mailboxer folder in lib folder of the project. I found that it is not needed for my project and so I deleted that which resolved my issue</p>\n", "tags": ["ruby-on-rails", "factory-girl", "rspec-rails"], "creation_date": 1477714317, "score": 0, "last_activity_date": 1477714317, "answer_id": 40315955, "is_accepted": true, "owner": {"user_id": 6642855, "reputation": 22, "user_type": "registered", "accept_rate": 67, "display_name": "Sachin", "link": "http://stackoverflow.com/users/6642855/sachin", "profile_image": "https://i.stack.imgur.com/ivpLm.jpg?s=128&g=1"}, "title": "Errbit error in Rails test", "question_id": 39137235}