{"tags": ["java", "javaparser"], "is_answered": false, "creation_date": 1473871560, "view_count": 46, "score": 0, "last_activity_date": 1477674970, "title": "Javaparser method editing", "answer_count": 1, "owner": {"user_id": 3503732, "reputation": 13, "user_type": "registered", "display_name": "tomwyn", "link": "http://stackoverflow.com/users/3503732/tomwyn", "profile_image": "https://www.gravatar.com/avatar/08934c44944d393f0b3f932e9758004c?s=128&d=identicon&r=PG&f=1"}, "link": "http://stackoverflow.com/questions/39495748/javaparser-method-editing", "question_id": 39495748}