{"is_answered": true, "view_count": 14, "last_activity_date": 1477727373, "answer_count": 2, "link": "http://stackoverflow.com/questions/40202923/to-convert-a-property-in-maven-pom-file-and-copy-it-to-a-particular-location", "question_id": 40202923, "tags": ["maven-3"], "creation_date": 1477225823, "accepted_answer_id": 40202972, "score": 0, "title": "To convert a property in maven pom file and copy it to a particular location", "owner": {"user_id": 6568829, "reputation": 3, "user_type": "registered", "display_name": "Abhishek Yadav", "link": "http://stackoverflow.com/users/6568829/abhishek-yadav", "profile_image": "https://lh3.googleusercontent.com/-sbkKXfPHh9c/AAAAAAAAAAI/AAAAAAAAFyU/cQ4YqBLGja8/photo.jpg?sz=128"}}