{"answer_count": 1, "view_count": 18, "last_activity_date": 1477737223, "is_answered": false, "last_edit_date": 1477576925, "link": "http://stackoverflow.com/questions/40202917/event-observer-is-not-working-in-magento", "tags": ["php", "events", "magento-1.9"], "creation_date": 1477225792, "score": 0, "title": "Event observer is not working in magento", "question_id": 40202917, "owner": {"user_id": 6180051, "reputation": 2, "user_type": "registered", "accept_rate": 0, "display_name": "Brindha", "link": "http://stackoverflow.com/users/6180051/brindha", "profile_image": "https://www.gravatar.com/avatar/eff844a99aba53ae4e432f0773e709f9?s=128&d=identicon&r=PG&f=1"}}