{"tags": ["windows", "visual-studio", "uwp"], "is_answered": true, "creation_date": 1476961806, "view_count": 119, "score": 3, "last_activity_date": 1477732792, "title": "Universal Windows Platform app registration fails - blocked by AppLocker", "answer_count": 1, "owner": {"user_id": 6015101, "reputation": 152, "user_type": "registered", "accept_rate": 50, "display_name": "Steve", "link": "http://stackoverflow.com/users/6015101/steve", "profile_image": "https://www.gravatar.com/avatar/7ec6dc4a1157de963d5e047782ebab04?s=128&d=identicon&r=PG"}, "link": "http://stackoverflow.com/questions/40152760/universal-windows-platform-app-registration-fails-blocked-by-applocker", "question_id": 40152760}