{"is_answered": true, "view_count": 232, "last_activity_date": 1477822501, "answer_count": 5, "last_edit_date": 1477242217, "link": "http://stackoverflow.com/questions/40164454/fetching-data-from-mysql-database-using-php-displaying-it-in-a-wysiwyg-form-for", "question_id": 40164454, "tags": ["php", "html", "mysql", "twitter-bootstrap"], "creation_date": 1476997201, "accepted_answer_id": 40312569, "score": 5, "title": "fetching data from mysql database using php, Displaying it in a WYSIWYG form for editing", "owner": {"user_id": 7050074, "reputation": 28, "user_type": "registered", "display_name": "Dero3376", "link": "http://stackoverflow.com/users/7050074/dero3376", "profile_image": "https://www.gravatar.com/avatar/55b4c97305f7f460044779299df80362?s=128&d=identicon&r=PG&f=1"}}