{"is_answered": true, "view_count": 49, "last_activity_date": 1477712426, "answer_count": 4, "last_edit_date": 1477712426, "link": "http://stackoverflow.com/questions/39865526/big-integer-modular-exponentiation", "question_id": 39865526, "tags": ["c", "modulus", "exponentiation"], "creation_date": 1475642232, "accepted_answer_id": 40315799, "score": 1, "title": "Big Integer Modular Exponentiation", "owner": {"user_id": 5447454, "reputation": 27, "user_type": "registered", "accept_rate": 80, "display_name": "Ronald Sumbayak", "link": "http://stackoverflow.com/users/5447454/ronald-sumbayak", "profile_image": "https://www.gravatar.com/avatar/4191aeb9a860f591fb91dd987143e46f?s=128&d=identicon&r=PG&f=1"}}