{"answer_count": 2, "view_count": 812, "last_activity_date": 1477771890, "is_answered": true, "last_edit_date": 1455761146, "link": "http://stackoverflow.com/questions/35108839/error-using-babel-relay-plugin", "tags": ["javascript", "webpack", "babeljs", "relayjs"], "creation_date": 1454199388, "score": 0, "title": "Error using babel-relay-plugin", "question_id": 35108839, "owner": {"user_id": 3243124, "reputation": 280, "user_type": "registered", "accept_rate": 45, "display_name": "AJ_1310", "link": "http://stackoverflow.com/users/3243124/aj-1310", "profile_image": "https://www.gravatar.com/avatar/e6526d2b3a6432d8d50ecc8ce6e7305f?s=128&d=identicon&r=PG&f=1"}}