{"tags": ["php", "fullcalendar", "eventsource"], "is_answered": false, "creation_date": 1476333764, "view_count": 23, "score": 0, "last_activity_date": 1477728001, "title": "NetworkError: 403 Forbidden when assign eventsourcr to full calender", "answer_count": 1, "owner": {"user_id": 4975179, "reputation": 474, "user_type": "registered", "accept_rate": 68, "display_name": "Archish", "link": "http://stackoverflow.com/users/4975179/archish", "profile_image": "https://www.gravatar.com/avatar/5d163944167cfe25314464fac1f9c158?s=128&d=identicon&r=PG&f=1"}, "link": "http://stackoverflow.com/questions/40012443/networkerror-403-forbidden-when-assign-eventsourcr-to-full-calender", "question_id": 40012443}