{"answer_count": 3, "view_count": 41, "last_activity_date": 1477763544, "is_answered": false, "last_edit_date": 1475008874, "link": "http://stackoverflow.com/questions/39733787/get-the-registry-key-of-installed-programs-php", "tags": ["php", "powershell", "key", "registry", "wscript"], "creation_date": 1475008355, "score": 0, "title": "Get the registry key of installed programs php", "question_id": 39733787, "owner": {"user_id": 5773297, "reputation": 29, "user_type": "registered", "accept_rate": 82, "display_name": "Jur Hillebrink", "link": "http://stackoverflow.com/users/5773297/jur-hillebrink", "profile_image": "https://www.gravatar.com/avatar/645f1c60d2d5fc39921ea2f951078f3b?s=128&d=identicon&r=PG&f=1"}}