{"website_url": "", "creation_date": 1331886831, "last_access_date": 1477761863, "badge_counts": {"bronze": 39, "silver": 14, "gold": 4}, "is_employee": false, "reputation_change_quarter": -130, "account_id": 1329339, "profile_image": "https://www.gravatar.com/avatar/d782c82af396a1b89eaaa199d662bafa?s=128&d=identicon&r=PG", "link": "http://stackoverflow.com/users/1273551/suamikim", "user_id": 1273551, "last_modified_date": 1456574581, "reputation_change_week": 50, "reputation": 214, "user_type": "registered", "display_name": "suamikim", "reputation_change_month": -130, "accept_rate": 80, "reputation_change_day": 5, "reputation_change_year": 119}