{"website_url": "https://gist.github.com/aleksey-bykov", "creation_date": 1247765729, "last_access_date": 1477739951, "badge_counts": {"bronze": 76, "silver": 32, "gold": 5}, "is_employee": false, "reputation_change_quarter": 90, "account_id": 47197, "profile_image": "https://i.stack.imgur.com/ASNeP.jpg?s=128&g=1", "link": "http://stackoverflow.com/users/139667/aleksey-bykov", "user_id": 139667, "last_modified_date": 1470836539, "reputation_change_week": 25, "reputation": 4955, "user_type": "registered", "display_name": "Aleksey Bykov", "reputation_change_month": 90, "accept_rate": 36, "reputation_change_day": 5, "reputation_change_year": 1191}