{"website_url": "", "creation_date": 1360173340, "last_access_date": 1477771083, "age": 24, "badge_counts": {"bronze": 68, "silver": 22, "gold": 5}, "is_employee": false, "reputation_change_quarter": 57, "account_id": 2335547, "profile_image": "https://i.stack.imgur.com/WY0Zw.png?s=128&g=1", "link": "http://stackoverflow.com/users/2047987/cilenco", "user_id": 2047987, "location": "Germany", "last_modified_date": 1476826662, "reputation_change_week": -2, "reputation": 1511, "user_type": "registered", "display_name": "Cilenco", "reputation_change_month": 57, "accept_rate": 80, "reputation_change_day": 0, "reputation_change_year": 479}