{"creation_date": 1412801785, "last_access_date": 1477656777, "badge_counts": {"bronze": 7, "silver": 0, "gold": 0}, "is_employee": false, "reputation_change_quarter": 0, "account_id": 5147344, "profile_image": "https://www.gravatar.com/avatar/03e6ee4f34b37497ce4c7a5ba700869a?s=128&d=identicon&r=PG&f=1", "link": "http://stackoverflow.com/users/4122931/zexco2", "user_id": 4122931, "last_modified_date": 1468678164, "reputation_change_week": 0, "reputation": 49, "user_type": "registered", "display_name": "zexco2", "reputation_change_month": 0, "accept_rate": 47, "reputation_change_day": 0, "reputation_change_year": 3}