{"website_url": "http://stackoverflow.com/users/418343/just-name", "creation_date": 1281612991, "last_access_date": 1477765935, "badge_counts": {"bronze": 256, "silver": 122, "gold": 28}, "is_employee": false, "reputation_change_quarter": -65, "account_id": 183141, "profile_image": "https://i.stack.imgur.com/7pgAk.jpg?s=128&g=1", "link": "http://stackoverflow.com/users/418343/anyname-donotcare", "user_id": 418343, "location": "Egypt", "last_modified_date": 1475050720, "reputation_change_week": 5, "reputation": 1192, "user_type": "registered", "display_name": "Anyname Donotcare", "reputation_change_month": -65, "accept_rate": 85, "reputation_change_day": 5, "reputation_change_year": -132}