{"website_url": "", "creation_date": 1282063130, "last_access_date": 1477776980, "badge_counts": {"bronze": 79, "silver": 38, "gold": 3}, "is_employee": false, "reputation_change_quarter": -155, "account_id": 186022, "profile_image": "https://www.gravatar.com/avatar/ced7f76fd1b5573ce3bdce2f3392df04?s=128&d=identicon&r=PG", "link": "http://stackoverflow.com/users/423105/larsh", "user_id": 423105, "location": "US", "last_modified_date": 1477652173, "reputation_change_week": -200, "reputation": 18063, "user_type": "registered", "display_name": "LarsH", "reputation_change_month": -155, "accept_rate": 74, "reputation_change_day": 5, "reputation_change_year": 686}