{"creation_date": 1262017910, "last_access_date": 1477691040, "badge_counts": {"bronze": 99, "silver": 40, "gold": 7}, "is_employee": false, "reputation_change_quarter": 5, "account_id": 187431, "profile_image": "https://www.gravatar.com/avatar/3e2a73b340277a2e2ec80657bebc50a7?s=128&d=identicon&r=PG", "link": "http://stackoverflow.com/users/425481/vbnewbie", "user_id": 425481, "location": "United States", "last_modified_date": 1477719501, "reputation_change_week": -2, "reputation": 1336, "user_type": "registered", "display_name": "vbNewbie", "reputation_change_month": 5, "accept_rate": 60, "reputation_change_day": -2, "reputation_change_year": 111}