{"creation_date": 1419283810, "last_access_date": 1477602980, "badge_counts": {"bronze": 12, "silver": 1, "gold": 0}, "is_employee": false, "reputation_change_quarter": 25, "account_id": 5524810, "profile_image": "https://www.gravatar.com/avatar/f2c9512ee4dac8ccbbf45fc2cf1a8046?s=128&d=identicon&r=PG&f=1", "link": "http://stackoverflow.com/users/4386626/toddt", "user_id": 4386626, "last_modified_date": 1477718945, "reputation_change_week": 11, "reputation": 180, "user_type": "registered", "display_name": "ToddT", "reputation_change_month": 25, "accept_rate": 62, "reputation_change_day": 2, "reputation_change_year": 137}