{"website_url": "", "creation_date": 1427733113, "last_access_date": 1477752687, "badge_counts": {"bronze": 5, "silver": 0, "gold": 0}, "is_employee": false, "reputation_change_quarter": 0, "account_id": 6024479, "profile_image": "https://www.gravatar.com/avatar/f5ccb4aa87c95f76fb6bdd93ab486710?s=128&d=identicon&r=PG&f=1", "link": "http://stackoverflow.com/users/4730644/tza", "user_id": 4730644, "last_modified_date": 1454480006, "reputation_change_week": 0, "reputation": 23, "user_type": "registered", "display_name": "tza", "reputation_change_month": 0, "reputation_change_day": 0, "reputation_change_year": 15}