{"website_url": "", "creation_date": 1464030279, "last_access_date": 1477699952, "badge_counts": {"bronze": 7, "silver": 1, "gold": 0}, "is_employee": false, "reputation_change_quarter": 5, "account_id": 8499229, "profile_image": "https://lh6.googleusercontent.com/-Z3FDdMPRutc/AAAAAAAAAAI/AAAAAAAAMoM/MgvHFoMZvfM/photo.jpg?sz=128", "link": "http://stackoverflow.com/users/6372837/adam-j", "user_id": 6372837, "last_modified_date": 1475608643, "reputation_change_week": 5, "reputation": 29, "user_type": "registered", "display_name": "Adam j", "reputation_change_month": 5, "accept_rate": 100, "reputation_change_day": 0, "reputation_change_year": 28}