{"creation_date": 1464749138, "last_access_date": 1477748273, "badge_counts": {"bronze": 8, "silver": 0, "gold": 0}, "is_employee": false, "reputation_change_quarter": 22, "account_id": 8550214, "profile_image": "https://www.gravatar.com/avatar/2357ece8af217eb2405cdb5ab041e001?s=128&d=identicon&r=PG&f=1", "link": "http://stackoverflow.com/users/6407353/corey-f", "user_id": 6407353, "location": "Toronto, ON, Canada", "last_modified_date": 1466100348, "reputation_change_week": 5, "reputation": 237, "user_type": "registered", "display_name": "Corey F", "reputation_change_month": 22, "accept_rate": 80, "reputation_change_day": 0, "reputation_change_year": 236}