{"creation_date": 1476883364, "last_access_date": 1477748448, "badge_counts": {"bronze": 2, "silver": 0, "gold": 0}, "is_employee": false, "reputation_change_quarter": 2, "account_id": 9471958, "profile_image": "https://www.gravatar.com/avatar/31c89661ccbf770fdea0c0eab8ed8987?s=128&d=identicon&r=PG&f=1", "link": "http://stackoverflow.com/users/7042559/britchey", "user_id": 7042559, "last_modified_date": 1477699306, "reputation_change_week": 2, "reputation": 3, "user_type": "registered", "display_name": "britchey", "reputation_change_month": 2, "reputation_change_day": 2, "reputation_change_year": 2}