{"last_access_date": 1477747557, "user_type": "registered", "badge_counts": {"bronze": 3, "silver": 0, "gold": 0}, "reputation_change_year": 8, "reputation_change_quarter": 8, "account_id": 9518907, "profile_image": "https://www.gravatar.com/avatar/65853f280d93b0df56791994e0717350?s=128&d=identicon&r=PG&f=1", "link": "http://stackoverflow.com/users/7074392/rsmooo", "user_id": 7074392, "creation_date": 1477476131, "reputation": 9, "reputation_change_month": 8, "display_name": "rsmooo", "reputation_change_week": 8, "reputation_change_day": -2, "is_employee": false}