{"creation_date": 1316810898, "last_access_date": 1475101990, "badge_counts": {"bronze": 21, "silver": 7, "gold": 2}, "is_employee": false, "reputation_change_quarter": 5, "account_id": 932336, "profile_image": "https://www.gravatar.com/avatar/8cfc9452be68ecc4901dcc83b26e1a9f?s=128&d=identicon&r=PG", "link": "http://stackoverflow.com/users/961950/lee", "user_id": 961950, "last_modified_date": 1339319775, "reputation_change_week": 0, "reputation": 459, "user_type": "registered", "display_name": "Lee", "reputation_change_month": 5, "accept_rate": 86, "reputation_change_day": 0, "reputation_change_year": 76}