{"creation_date": 1317214506, "last_access_date": 1477663907, "badge_counts": {"bronze": 37, "silver": 14, "gold": 2}, "is_employee": false, "reputation_change_quarter": 3, "account_id": 941039, "profile_image": "https://www.gravatar.com/avatar/4f54ad6e06546aedf024dfcda9406724?s=128&d=identicon&r=PG", "link": "http://stackoverflow.com/users/969113/user969113", "user_id": 969113, "last_modified_date": 1432154137, "reputation_change_week": -2, "reputation": 665, "user_type": "registered", "display_name": "user969113", "reputation_change_month": 3, "accept_rate": 57, "reputation_change_day": -2, "reputation_change_year": 70}