{"answer_count": 1, "view_count": 32, "last_activity_date": 1477704651, "is_answered": false, "last_edit_date": 1477315239, "link": "http://stackoverflow.com/questions/40219226/java-calling-js-with-rihno-uint8array-is-not-defined", "tags": ["javascript", "java", "arrays", "call", "rhino"], "creation_date": 1477314249, "score": 2, "title": "Java calling JS with Rihno (Uint8Array is not defined)", "question_id": 40219226, "owner": {"user_id": 967143, "reputation": 746, "user_type": "registered", "accept_rate": 46, "display_name": "Johny19", "link": "http://stackoverflow.com/users/967143/johny19", "profile_image": "https://www.gravatar.com/avatar/348299fd90e68b310fc75c3c96a6ad58?s=128&d=identicon&r=PG"}}