{"answer_count": 1, "view_count": 22, "last_activity_date": 1477699228, "is_answered": true, "last_edit_date": 1477549101, "link": "http://stackoverflow.com/questions/40271840/talend-retry-subjob-based-on-rest-request-results", "tags": ["rest", "talend"], "creation_date": 1477514828, "score": 1, "title": "talend - retry subjob based on REST request results", "question_id": 40271840, "owner": {"user_id": 791657, "reputation": 2045, "user_type": "registered", "accept_rate": 73, "display_name": "Jay Rizzi", "link": "http://stackoverflow.com/users/791657/jay-rizzi", "profile_image": "https://www.gravatar.com/avatar/54e0e649819bb01f6a37e92937fb5071?s=128&d=identicon&r=PG"}}