{"answer_count": 0, "view_count": 11, "last_activity_date": 1477732663, "is_answered": false, "last_edit_date": 1477732663, "link": "http://stackoverflow.com/questions/40316880/which-connection-string-fields-are-mandatory", "tags": [".net", "ado.net", "connection-string"], "creation_date": 1477724787, "score": -1, "title": "Which connection string fields are mandatory?", "question_id": 40316880, "owner": {"user_id": 235671, "reputation": 3699, "user_type": "registered", "accept_rate": 81, "display_name": "t3chb0t", "link": "http://stackoverflow.com/users/235671/t3chb0t", "profile_image": "https://i.stack.imgur.com/NjgvO.png?s=128&g=1"}}