{"answer_count": 2, "view_count": 30, "last_activity_date": 1477858798, "is_answered": true, "last_edit_date": 1477851788, "link": "http://stackoverflow.com/questions/40324556/responsive-design-how-to-create-two-div-side-by-side-one-fluid-and-one-fixed", "tags": ["html", "css", "css3", "responsive-design"], "creation_date": 1477782673, "score": -6, "title": "Responsive Design: How to create two &lt;div&gt; side by side: one fluid and one fixed?", "question_id": 40324556, "owner": {"user_id": 5291479, "reputation": 293, "user_type": "registered", "accept_rate": 34, "display_name": "Jo Ko", "link": "http://stackoverflow.com/users/5291479/jo-ko", "profile_image": "https://www.gravatar.com/avatar/5af8c3b94bfacf96b56f34cea04cff25?s=128&d=identicon&r=PG&f=1"}}