{"answer_count": 2, "view_count": 28, "last_activity_date": 1477764949, "is_answered": true, "last_edit_date": 1477764949, "link": "http://stackoverflow.com/questions/40250907/going-back-and-forth-with-methods-in-java", "tags": ["java"], "creation_date": 1477435291, "score": -2, "title": "Going back and forth with methods in Java", "question_id": 40250907, "owner": {"user_id": 7010232, "reputation": 4, "user_type": "registered", "display_name": "pellepelle", "link": "http://stackoverflow.com/users/7010232/pellepelle", "profile_image": "https://www.gravatar.com/avatar/b63b627b8bebe79f0d0687264314c0f3?s=128&d=identicon&r=PG&f=1"}}