{"tags": ["redis"], "is_answered": false, "creation_date": 1477546154, "view_count": 11, "score": 0, "last_activity_date": 1477749009, "title": "redis keys command delete data but scan command does not", "answer_count": 1, "owner": {"user_id": 6703237, "reputation": 1, "user_type": "registered", "display_name": "Isha Nagpal", "link": "http://stackoverflow.com/users/6703237/isha-nagpal", "profile_image": "https://www.gravatar.com/avatar/17dbdd977bb8f8b7d49330c20d8b3e51?s=128&d=identicon&r=PG&f=1"}, "link": "http://stackoverflow.com/questions/40276773/redis-keys-command-delete-data-but-scan-command-does-not", "question_id": 40276773}