{"tags": ["isis"], "is_answered": true, "creation_date": 1477577415, "view_count": 11, "score": 1, "last_activity_date": 1477725297, "title": "How to order collection columns in Apache isis?", "answer_count": 1, "owner": {"user_id": 2350202, "reputation": 41, "user_type": "registered", "display_name": "Marcel Baumann", "link": "http://stackoverflow.com/users/2350202/marcel-baumann", "profile_image": "https://www.gravatar.com/avatar/729d43a996df6aeecbe722f393048e21?s=128&d=identicon&r=PG"}, "link": "http://stackoverflow.com/questions/40286855/how-to-order-collection-columns-in-apache-isis", "question_id": 40286855}