{"answer_count": 2, "view_count": 45, "last_activity_date": 1477684339, "is_answered": true, "last_edit_date": 1477585501, "link": "http://stackoverflow.com/questions/40289530/bash-write-read-to-from-array", "tags": ["arrays", "bash", "if-statement"], "creation_date": 1477584684, "score": 0, "title": "Bash write/read to/from array", "question_id": 40289530, "owner": {"user_id": 7081351, "reputation": 1, "user_type": "registered", "display_name": "h3938116", "link": "http://stackoverflow.com/users/7081351/h3938116", "profile_image": "https://www.gravatar.com/avatar/95d40af203d32a5feaba85e67b8b5bdb?s=128&d=identicon&r=PG&f=1"}}