{"answer_count": 1, "view_count": 10, "last_activity_date": 1477676296, "is_answered": false, "last_edit_date": 1477676068, "link": "http://stackoverflow.com/questions/40295792/compatible-versions-of-gradle-sonar-clover-plugin", "tags": ["gradle", "sonarqube", "gradle-plugin", "sonarqube-scan", "clover"], "creation_date": 1477611185, "score": 0, "title": "Compatible versions of Gradle, Sonar, clover plugin?", "question_id": 40295792, "owner": {"user_id": 2829987, "reputation": 44, "user_type": "registered", "accept_rate": 62, "display_name": "lex", "link": "http://stackoverflow.com/users/2829987/lex", "profile_image": "https://www.gravatar.com/avatar/a656c4d04c9b6396c6ed165f73fb056e?s=128&d=identicon&r=PG&f=1"}}