{"answer_count": 2, "view_count": 46, "last_activity_date": 1477677353, "is_answered": false, "last_edit_date": 1477606753, "link": "http://stackoverflow.com/questions/40294969/excel-concatenate-all-values-with-same-number-assigned-in-row", "tags": ["excel", "vba", "excel-vba"], "creation_date": 1477606033, "score": 0, "title": "Excel - Concatenate all values with same number assigned in row", "question_id": 40294969, "owner": {"user_id": 7072499, "reputation": 1, "user_type": "registered", "display_name": "R Mannix", "link": "http://stackoverflow.com/users/7072499/r-mannix", "profile_image": "https://www.gravatar.com/avatar/c52ab1d4406d04f41658e8d5e1242e65?s=128&d=identicon&r=PG&f=1"}}