{"tags": ["php", "wordpress", "apache", ".htaccess", "permalinks"], "is_answered": false, "creation_date": 1477604813, "view_count": 47, "score": 1, "last_activity_date": 1477670131, "title": "Wordpress site getting 404 if &quot;Permalink&quot; option set to &quot;Post name&quot;", "answer_count": 3, "owner": {"user_id": 2266042, "reputation": 1620, "user_type": "registered", "accept_rate": 74, "display_name": "John Crawford", "link": "http://stackoverflow.com/users/2266042/john-crawford", "profile_image": "https://www.gravatar.com/avatar/78bba49bd539fb064b8bcf79874703d0?s=128&d=identicon&r=PG"}, "link": "http://stackoverflow.com/questions/40294713/wordpress-site-getting-404-if-permalink-option-set-to-post-name", "question_id": 40294713}