{"answer_count": 1, "view_count": 13, "last_activity_date": 1477736530, "is_answered": false, "last_edit_date": 1477736530, "link": "http://stackoverflow.com/questions/40290146/how-to-control-vmware-tools-installation-with-salt-cloud-using-vmware-provider", "tags": ["salt-stack", "vmware-tools", "salt-cloud"], "creation_date": 1477586825, "score": 0, "title": "How to control vmware tools installation with salt-cloud using vmware provider", "question_id": 40290146, "owner": {"user_id": 5992118, "reputation": 839, "user_type": "registered", "display_name": "dahrens", "link": "http://stackoverflow.com/users/5992118/dahrens", "profile_image": "https://www.gravatar.com/avatar/08ae2e7ce567cbfb93d480892bd10fa0?s=128&d=identicon&r=PG"}}